<?xml version="1.0"?>
<Results version="1.0">
<ReportNode type="testrun">
<ReportNode type="Iteration">
<ReportNode type="Action">
<Data>
    <Name>Action1</Name>
    <Description />
    <StartTime>2022-05-11 14:45:55</StartTime>
    <Result>Done</Result>
    <InputParameters />
    <Extension>
      <IconKey>6fbd4cfb210d448483b90ca964c14c73</IconKey>
      <IsPlainTextNodeName>True</IsPlainTextNodeName>
    </Extension>
  </Data>
</ReportNode>
<ReportNode type="Action">
<Data>
    <Name>SecondPunkt</Name>
    <Description />
    <StartTime>2022-05-11 14:45:55</StartTime>
    <Result>Done</Result>
    <InputParameters />
    <Extension>
      <IconKey>6fbd4cfb210d448483b90ca964c14c73</IconKey>
      <IsPlainTextNodeName>True</IsPlainTextNodeName>
    </Extension>
  </Data>
</ReportNode>
<ReportNode type="Action">
<Data>
    <Name>TredjePunkt</Name>
    <Description />
    <StartTime>2022-05-11 14:45:57</StartTime>
    <Result>Done</Result>
    <InputParameters />
    <Extension>
      <IconKey>6fbd4cfb210d448483b90ca964c14c73</IconKey>
      <IsPlainTextNodeName>True</IsPlainTextNodeName>
    </Extension>
  </Data>
</ReportNode>
<Data>
    <Name>Action0</Name>
    <Description />
    <StartTime>2022-05-11 14:45:54</StartTime>
    <Duration>3</Duration>
    <Result>Done</Result>
    <Extension>
      <IconKey>bcc624efc709400e808186290d440cde</IconKey>
      <IsPlainTextNodeName>True</IsPlainTextNodeName>
    </Extension>
    <Index>1</Index>
    <TestedApplications />
  </Data>
</ReportNode>
<Data>
    <Name>SecondWBScript</Name>
    <ToolName>Micro Focus UFT One</ToolName>
    <ToolVersion>2021</ToolVersion>
    <ToolVersionStringLiteral>2021</ToolVersionStringLiteral>
    <Description />
    <StartTime>2022-05-11 14:45:54</StartTime>
    <Duration>3</Duration>
    <Result>Done</Result>
    <InputParameters />
    <Extension>
      <IconKey>81946afc9e864d3ca0b70f96155af02e</IconKey>
      <IsPlainTextNodeName>True</IsPlainTextNodeName>
    </Extension>
    <Environment>
      <Timezone>+02:00:00</Timezone>
      <Locale>svenska (Sverige)</Locale>
      <User>AzureAD\AmerRasheed</User>
      <CpuInfo>11th Gen Intel(R) Core(TM) i7-1165G7 @ 2.80GHz</CpuInfo>
      <NumberOfCores>8</NumberOfCores>
      <TotalMemory>16064</TotalMemory>
      <HostName>\LEM-5CG2109VW2</HostName>
      <OSInfo>Windows 10 21H2 (x64)</OSInfo>
    </Environment>
    <TestedApplications />
    <Links>
      <Link type="DataTable" reference="Default.xlsx" displayname="Default Data Table" />
    </Links>
  </Data>
</ReportNode>
<GeneralInfo>
    <ResultName>Res90</ResultName>
    <RunStartTime>2022-05-11 14:45:54</RunStartTime>
    <Timezone>+02:00:00</Timezone>
    <OrchestrationToolName>Micro Focus UFT One</OrchestrationToolName>
    <OrchestrationToolVersion>2021</OrchestrationToolVersion>
    <OrchestrationToolVersionStringLiteral>2021</OrchestrationToolVersionStringLiteral>
  </GeneralInfo>
</Results>