<?xml version="1.0"?>
<Results version="1.0">
<ReportNode type="testrun">
<ReportNode type="Iteration">
<ReportNode type="Action">
<Data>
    <Name>Action1</Name>
    <Description />
    <StartTime>2022-05-11 13:40:24</StartTime>
    <Result>Done</Result>
    <InputParameters />
    <Extension>
      <IconKey>1da75a3fe4104cc6904a8b1c02b702e2</IconKey>
      <IsPlainTextNodeName>True</IsPlainTextNodeName>
    </Extension>
  </Data>
</ReportNode>
<ReportNode type="Action">
<Data>
    <Name>SecondPunkt</Name>
    <Description />
    <StartTime>2022-05-11 13:40:25</StartTime>
    <Result>Done</Result>
    <InputParameters />
    <Extension>
      <IconKey>1da75a3fe4104cc6904a8b1c02b702e2</IconKey>
      <IsPlainTextNodeName>True</IsPlainTextNodeName>
    </Extension>
  </Data>
</ReportNode>
<ReportNode type="Action">
<ReportNode type="Step">
<Data>
    <Name>Ogiltig 'exit'-instruktion</Name>
    <ErrorText>Ogiltig 'exit'-instruktion</ErrorText>
    <Description>&lt;BR/&gt;Line (17): &amp;quot;Exit For&amp;quot;.</Description>
    <StartTime>2022-05-11 13:40:46</StartTime>
    <Result>Failed</Result>
    <Extension>
      <IconKey>4352ec2568c44709956f92ec86e52bdf</IconKey>
      <IsPlainTextNodeName>True</IsPlainTextNodeName>
      <MergeIsErrorIcon>True</MergeIsErrorIcon>
    </Extension>
    <Snapshot reference="Resources\Snapshots\91dcce07-bce1-4931-957b-0c5bd6cda851.jpeg" />
    <DeviceInfo />
  </Data>
</ReportNode>
<ReportNode type="Step">
<Data>
    <Name>Stop Run</Name>
    <Description>Run stopped by user.</Description>
    <StartTime>2022-05-11 13:40:53</StartTime>
    <Result>Information</Result>
    <Extension>
      <IconKey>e6b6fe3ba3f64444be3c3273ca74a6d0</IconKey>
      <IsPlainTextNodeName>True</IsPlainTextNodeName>
    </Extension>
    <Snapshot reference="Resources\Snapshots\b736c62a-cb66-4ec9-a35f-b6715148603f.jpeg" />
  </Data>
</ReportNode>
<Data>
    <Name>TredjePunkt</Name>
    <Description />
    <StartTime>2022-05-11 13:40:46</StartTime>
    <Duration>7</Duration>
    <Result>Failed</Result>
    <InputParameters />
    <Extension>
      <IconKey>1da75a3fe4104cc6904a8b1c02b702e2</IconKey>
      <IsPlainTextNodeName>True</IsPlainTextNodeName>
    </Extension>
  </Data>
</ReportNode>
<Data>
    <Name>Action0</Name>
    <Description />
    <StartTime>2022-05-11 13:40:24</StartTime>
    <Duration>29</Duration>
    <Result>Failed</Result>
    <Extension>
      <IconKey>18eeff59d2c247d4a641264e81a58148</IconKey>
      <IsPlainTextNodeName>True</IsPlainTextNodeName>
    </Extension>
    <Index>1</Index>
    <TestedApplications />
  </Data>
</ReportNode>
<Data>
    <Name>SecondWBScript</Name>
    <ToolName>Micro Focus UFT One</ToolName>
    <ToolVersion>2021</ToolVersion>
    <ToolVersionStringLiteral>2021</ToolVersionStringLiteral>
    <Description />
    <StartTime>2022-05-11 13:40:23</StartTime>
    <Duration>30</Duration>
    <Result>Failed</Result>
    <InputParameters />
    <Extension>
      <IconKey>f8f8893e916147a48b1dcd050ce2e80d</IconKey>
      <IsPlainTextNodeName>True</IsPlainTextNodeName>
    </Extension>
    <Environment>
      <Timezone>+02:00:00</Timezone>
      <Locale>svenska (Sverige)</Locale>
      <User>AzureAD\AmerRasheed</User>
      <CpuInfo>11th Gen Intel(R) Core(TM) i7-1165G7 @ 2.80GHz</CpuInfo>
      <NumberOfCores>8</NumberOfCores>
      <TotalMemory>16064</TotalMemory>
      <HostName>\LEM-5CG2109VW2</HostName>
      <OSInfo>Windows 10 21H2 (x64)</OSInfo>
    </Environment>
    <TestedApplications />
    <Links>
      <Link type="DataTable" reference="Default.xlsx" displayname="Default Data Table" />
    </Links>
  </Data>
</ReportNode>
<GeneralInfo>
    <ResultName>Res69</ResultName>
    <RunStartTime>2022-05-11 13:40:23</RunStartTime>
    <Timezone>+02:00:00</Timezone>
    <OrchestrationToolName>Micro Focus UFT One</OrchestrationToolName>
    <OrchestrationToolVersion>2021</OrchestrationToolVersion>
    <OrchestrationToolVersionStringLiteral>2021</OrchestrationToolVersionStringLiteral>
  </GeneralInfo>
</Results>